[
	{
		"name": "Evil Perth",
		"leaderName": "Gina Rinehart",
		"adjective": ["Urban Development"],
		"startBias": ["Coast"],
		"preferredVictoryType": "Culteral",
		
		"startIntroPart1": "Embrace the darkness, the den of conformity and order that is Evil Perth",
		"startIntroPart2": "You are Perth's financial leader, Gina Rinehart, whom the Perthites expect to guide them to a darker future.",
		
		"declaringWar": "Try it again, I dare ya",
		"attacked": "She'll be right!",
		"defeated": "Oi",
		"introduction": "Embrace the darkness, the den of conformity and order that is Evil Perth",
		
		"neutralHello": "G'day.",
		"hateHello": "FUCK OFF.",
		
		
		"afterPeace": "Nice one.",
		"tradeRequest": "Come on you'd be more humble without it.",

		"outerColor": [0,48,135],
		"innerColor": [242,169,0],
		"uniques": [
                  ""Enables conversion of city production to [Culture] <after discovering [Architecture]>"",
		  "[+25]% Production when constructing [All] buildings [in all cities] <during a Golden Age>",
		  "[+25]% Strength <when attacking> <during a Golden Age>",   
		  "[+25]% of excess happiness converted to [Production] <during a Golden Age>",
		  "[+50]% Golden Age length",
		  "[+50]% unhappiness from the number of cities",
		  "[-50]% Unhappiness from [Population] [in all cities]"
			
		],
		"cities": ["The CBD","Subiaco","Mt Lawley","Inglewood","Mt Hawthorn","Leederville","Tuart Hill","High Gate","Stirling","Peppermint Grove","Cottesloe","City Beach","Applecross","City Beach","Victoria Park","Thornlie","Mirrabooka","Bayswater","Midvale","Kenwick","Kelmscott","Innaloo","Claremont","Nedlands","Trigg","Swanbourne"]
	}
]
